xfmido/__init__.py
xfmido/xfmido.py
xfmido-0.0.2.dist-info/METADATA
xfmido-0.0.2.dist-info/WHEEL
xfmido-0.0.2.dist-info/licenses/LICENSE
xfmido-0.0.2.dist-info/RECORD
