Metadata-Version: 2.3
Name: xfmido
Version: 0.0.2
Summary: A modified version of the Mido library to handle XF format MIDI files.
Project-URL: Homepage, https://github.com/jiroshimaya/xfmido
Author: shimajiroxyz
License: The MIT License
License-File: LICENSE
Keywords: midi,music,xfmido
Classifier: License :: OSI Approved :: MIT License
Classifier: Operating System :: OS Independent
Classifier: Programming Language :: Python :: 3.11
Requires-Python: >=3.11
Requires-Dist: mido~=1.3
